datadrivenquadrature/__init__.py
datadrivenquadrature/main.py
datadrivenquadrature-1.0.1.dist-info/LICENSE
datadrivenquadrature-1.0.1.dist-info/METADATA
datadrivenquadrature-1.0.1.dist-info/WHEEL
datadrivenquadrature-1.0.1.dist-info/top_level.txt
datadrivenquadrature-1.0.1.dist-info/RECORD
