Metadata-Version: 2.1
Name: datadrivenquadrature
Version: 1.0.1
Home-page: https://github.com/LDEO-CREW/data-driven-quadrature
Author: Neal Ma
License-File: LICENSE
Requires-Dist: numpy
Requires-Dist: xarray
Requires-Dist: cvxpy
